tls_test_tools/__init__.py
tls_test_tools-0.1.1.dist-info/LICENSE
tls_test_tools-0.1.1.dist-info/METADATA
tls_test_tools-0.1.1.dist-info/WHEEL
tls_test_tools-0.1.1.dist-info/top_level.txt
tls_test_tools-0.1.1.dist-info/RECORD
