Metadata-Version: 2.1
Name: tls-test-tools
Version: 0.1.1
Summary: A set of tools to quickly write unit tests for (m)TLS communication
Home-page: https://github.com/IBM/tls-test-tools
Author: Gabe Goodhart
Author-email: gabe.l.hart@gmail.com
License: APACHE
Platform: UNKNOWN
Classifier: Intended Audience :: Developers
Classifier: Programming Language :: Python :: 3
Classifier: Programming Language :: Python :: 3.7
Classifier: Programming Language :: Python :: 3.8
Classifier: Programming Language :: Python :: 3.9
Classifier: Programming Language :: Python :: 3.10
License-File: LICENSE
Requires-Dist: alchemy-logging (>=1.0.3)
Requires-Dist: cryptography (>=36.0.2)
